mediadata/__init__.py
mediadata/mediadata.py
mediadata/lib/Arguement.py
mediadata/lib/__init__.py
mediadata-1.0.7.dist-info/METADATA
mediadata-1.0.7.dist-info/WHEEL
mediadata-1.0.7.dist-info/entry_points.txt
mediadata-1.0.7.dist-info/top_level.txt
mediadata-1.0.7.dist-info/RECORD
